voda_sdk/__init__.py
voda_sdk/sdk.py
voda_sdk/utils.py
voda_sdk/grpc/__init__.py
voda_sdk/http/__init__.py
voda_sdk/http/sdk.py
voda_sdk-0.0.1.dist-info/LICENSE
voda_sdk-0.0.1.dist-info/METADATA
voda_sdk-0.0.1.dist-info/WHEEL
voda_sdk-0.0.1.dist-info/top_level.txt
voda_sdk-0.0.1.dist-info/RECORD
