Metadata-Version: 2.1
Name: voda-sdk
Version: 0.0.1
Summary: Software development kit for VODA AI Service (https://vodavision.ai)
Home-page: https://github.com/VODA-VISION-AI/voda-sdk-python
Author: Yeongbin Jo
Author-email: yeongbin.jo@vodavision.ai
License: MIT
Keywords: python
Platform: UNKNOWN
Classifier: Development Status :: 3 - Alpha
Classifier: Topic :: Software Development :: Testing
Classifier: Topic :: System :: Installation/Setup
Classifier: Topic :: Software Development :: Libraries :: Python Modules
Classifier: License :: OSI Approved :: MIT License
Classifier: Operating System :: MacOS :: MacOS X
Classifier: Operating System :: Microsoft :: Windows
Classifier: Programming Language :: Python :: 3
Classifier: Programming Language :: Python :: 3.9
Classifier: Programming Language :: Python :: 3.10
Requires-Python: >=3.9
License-File: LICENSE
Requires-Dist: requests
